langchain_mcts/__init__.py
langchain_mcts/core.py
langchain_mcts-0.2.0.dist-info/METADATA
langchain_mcts-0.2.0.dist-info/WHEEL
langchain_mcts-0.2.0.dist-info/top_level.txt
langchain_mcts-0.2.0.dist-info/RECORD
