Metadata-Version: 2.4
Name: langchain-mcts
Version: 0.2.0
Summary: Monte Carlo Tree Search integration for LangChain
Home-page: https://github.com/tu-usuario/langchain-mcts
Author: Tu Nombre
Author-email: Tu Nombre <tu@email.com>
License: MIT
Project-URL: Homepage, https://github.com/tu-usuario/langchain-mcts
Project-URL: Repository, https://github.com/tu-usuario/langchain-mcts
Project-URL: Documentation, https://langchain-mcts.readthedocs.io/
Classifier: Development Status :: 2 - Pre-Alpha
Classifier: Intended Audience :: Developers
Classifier: License :: OSI Approved :: MIT License
Classifier: Programming Language :: Python :: 3
Classifier: Programming Language :: Python :: 3.8
Classifier: Programming Language :: Python :: 3.9
Classifier: Programming Language :: Python :: 3.10
Classifier: Programming Language :: Python :: 3.11
Classifier: Programming Language :: Python :: 3.12
Classifier: Topic :: Scientific/Engineering :: Artificial Intelligence
Requires-Python: >=3.8
Requires-Dist: langchain>=0.1.0
Requires-Dist: numpy>=1.20.0
Provides-Extra: dev
Requires-Dist: pytest>=6.0; extra == "dev"
Requires-Dist: black; extra == "dev"
Requires-Dist: flake8; extra == "dev"
Requires-Dist: mypy; extra == "dev"
Dynamic: author
Dynamic: home-page
Dynamic: requires-python
